{
  "comp": 1,
  "form": 3,
  "title": "العلوم والفيزياء — النموذج الثالث",
  "questions": [
    {
      "text": "ما هو الجهاز الذي يقيس شدة الزلازل؟",
      "options": ["البارومتر", "السيزموغراف", "المانومتر", "الثرمومتر"],
      "correct": 1
    },
    {
      "text": "ما هو أكبر عضو في جسم الإنسان؟",
      "options": ["الكبد", "الرئة", "الجلد", "الدماغ"],
      "correct": 2
    },
    {
      "text": "ما الذي يُنتج الضوء في النجوم؟",
      "options": ["الاندماج النووي", "الانشطار النووي", "الاحتراق الكيميائي", "التفاعل الضوئي"],
      "correct": 0
    },
    {
      "text": "كم عدد الكروموسومات في خلية الإنسان السليمة؟",
      "options": ["23", "44", "46", "48"],
      "correct": 2
    },
    {
      "text": "ما هو الرمز الكيميائي للأكسجين؟",
      "options": ["Ox", "Ok", "O", "Og"],
      "correct": 2
    },
    {
      "text": "ما هو أسرع حيوان بري على وجه الأرض؟",
      "options": ["الأسد", "النمر", "الفهد", "الغزال"],
      "correct": 2
    },
    {
      "text": "ما هي مدة دوران الأرض حول الشمس؟",
      "options": ["24 ساعة", "30 يوماً", "365 يوماً", "366 يوماً"],
      "correct": 2
    },
    {
      "text": "أي من الآتي موصل جيد للكهرباء؟",
      "options": ["الخشب", "البلاستيك", "النحاس", "المطاط"],
      "correct": 2
    },
    {
      "text": "ما اسم النظرية التي تصف نشأة الكون؟",
      "options": ["نظرية التطور", "نظرية الانفجار العظيم", "نظرية الأوتار", "نظرية الكم"],
      "correct": 1
    },
    {
      "text": "ما هو أكثر المعادن وفرة في قشرة الأرض؟",
      "options": ["الحديد", "الألومنيوم", "الكالسيوم", "السيليكون"],
      "correct": 3
    },
    {
      "text": "ما اسم عملية تحويل الضوء إلى طاقة كيميائية في النباتات؟",
      "options": ["التنفس الخلوي", "التخمر", "البناء الضوئي", "الهضم"],
      "correct": 2
    },
    {
      "text": "كم تبلغ درجة الصفر المطلق تقريباً بالمئوية؟",
      "options": ["-100 °C", "-200 °C", "-273 °C", "-373 °C"],
      "correct": 2
    }
  ]
}
